Metadata-Version: 2.1
Name: tikit
Version: 1.9.5.260130
Summary: Kit for TI PLATFORM
Home-page: https://cloud.tencent.com/
Author: TI PLATFORM TEAM
Author-email: TI_Platform@tencent.com
License: MIT
Platform: UNKNOWN
Requires-Dist: certifi~=2021.10.8
Requires-Dist: click>=0.8.0
Requires-Dist: ConfigParser~=7.1.0
Requires-Dist: cos-python-sdk-v5~=1.9.29
Requires-Dist: cryptography>=3.4.8
Requires-Dist: prettytable~=2.5.0
Requires-Dist: PyHive~=0.6.4
Requires-Dist: PyJWT>=2.9.0
Requires-Dist: PyYAML~=6.0.2
Requires-Dist: requests>=2.26.0
Requires-Dist: setuptools~=56.0.0
Requires-Dist: tqdm>=4.64.0
